[{"name":"Adda-Douéni","country_name":"Comoros","state_name":"Anjouan","state_code":"A"},{"name":"Antsahé","country_name":"Comoros","state_name":"Anjouan","state_code":"A"},{"name":"Assimpao","country_name":"Comoros","state_name":"Anjouan","state_code":"A"},{"name":"Bambao","country_name":"Comoros","state_name":"Anjouan","state_code":"A"},{"name":"Bandajou","country_name":"Comoros","state_name":"Anjouan","state_code":"A"},{"name":"Barakani","country_name":"Comoros","state_name":"Anjouan","state_code":"A"},{"name":"Bimbini","country_name":"Comoros","state_name":"Anjouan","state_code":"A"},{"name":"Boungouéni","country_name":"Comoros","state_name":"Anjouan","state_code":"A"},{"name":"Chandra","country_name":"Comoros","state_name":"Anjouan","state_code":"A"},{"name":"Chironkamba","country_name":"Comoros","state_name":"Anjouan","state_code":"A"},{"name":"Chitrouni","country_name":"Comoros","state_name":"Anjouan","state_code":"A"},{"name":"Daji","country_name":"Comoros","state_name":"Anjouan","state_code":"A"},{"name":"Domoni","country_name":"Comoros","state_name":"Anjouan","state_code":"A"},{"name":"Dziani","country_name":"Comoros","state_name":"Anjouan","state_code":"A"},{"name":"Hajoho","country_name":"Comoros","state_name":"Anjouan","state_code":"A"},{"name":"Harembo","country_name":"Comoros","state_name":"Anjouan","state_code":"A"},{"name":"Kangani","country_name":"Comoros","state_name":"Anjouan","state_code":"A"},{"name":"Kavani","country_name":"Comoros","state_name":"Anjouan","state_code":"A"},{"name":"Koki","country_name":"Comoros","state_name":"Anjouan","state_code":"A"},{"name":"Koni-Djodjo","country_name":"Comoros","state_name":"Anjouan","state_code":"A"},{"name":"Koni-Ngani","country_name":"Comoros","state_name":"Anjouan","state_code":"A"},{"name":"Kyo","country_name":"Comoros","state_name":"Anjouan","state_code":"A"},{"name":"Limbi","country_name":"Comoros","state_name":"Anjouan","state_code":"A"},{"name":"Lingoni","country_name":"Comoros","state_name":"Anjouan","state_code":"A"},{"name":"Magnassini-Nindri","country_name":"Comoros","state_name":"Anjouan","state_code":"A"},{"name":"Maraharé","country_name":"Comoros","state_name":"Anjouan","state_code":"A"},{"name":"Mirontsi","country_name":"Comoros","state_name":"Anjouan","state_code":"A"},{"name":"Mjamaoué","country_name":"Comoros","state_name":"Anjouan","state_code":"A"},{"name":"Mjimandra","country_name":"Comoros","state_name":"Anjouan","state_code":"A"},{"name":"Moutsamoudou","country_name":"Comoros","state_name":"Anjouan","state_code":"A"},{"name":"Moya","country_name":"Comoros","state_name":"Anjouan","state_code":"A"},{"name":"Mramani","country_name":"Comoros","state_name":"Anjouan","state_code":"A"},{"name":"Mrémani","country_name":"Comoros","state_name":"Anjouan","state_code":"A"},{"name":"Ongoni","country_name":"Comoros","state_name":"Anjouan","state_code":"A"},{"name":"Ouani","country_name":"Comoros","state_name":"Anjouan","state_code":"A"},{"name":"Ouzini","country_name":"Comoros","state_name":"Anjouan","state_code":"A"},{"name":"Pajé","country_name":"Comoros","state_name":"Anjouan","state_code":"A"},{"name":"Patsi","country_name":"Comoros","state_name":"Anjouan","state_code":"A"},{"name":"Sima","country_name":"Comoros","state_name":"Anjouan","state_code":"A"},{"name":"Tsimbeo","country_name":"Comoros","state_name":"Anjouan","state_code":"A"},{"name":"Vouani","country_name":"Comoros","state_name":"Anjouan","state_code":"A"},{"name":"Bahani","country_name":"Comoros","state_name":"Grande Comore","state_code":"G"},{"name":"Bambadjani","country_name":"Comoros","state_name":"Grande Comore","state_code":"G"},{"name":"Bouni","country_name":"Comoros","state_name":"Grande Comore","state_code":"G"},{"name":"Chezani","country_name":"Comoros","state_name":"Grande Comore","state_code":"G"},{"name":"Chindini","country_name":"Comoros","state_name":"Grande Comore","state_code":"G"},{"name":"Chouani","country_name":"Comoros","state_name":"Grande Comore","state_code":"G"},{"name":"Dembéni","country_name":"Comoros","state_name":"Grande Comore","state_code":"G"},{"name":"Douniani","country_name":"Comoros","state_name":"Grande Comore","state_code":"G"},{"name":"Dzahadjou","country_name":"Comoros","state_name":"Grande Comore","state_code":"G"},{"name":"Foumbouni","country_name":"Comoros","state_name":"Grande Comore","state_code":"G"},{"name":"Hantsindzi","country_name":"Comoros","state_name":"Grande Comore","state_code":"G"},{"name":"Héroumbili","country_name":"Comoros","state_name":"Grande Comore","state_code":"G"},{"name":"Itsandra","country_name":"Comoros","state_name":"Grande Comore","state_code":"G"},{"name":"Itsandzéni","country_name":"Comoros","state_name":"Grande Comore","state_code":"G"},{"name":"Ivouani","country_name":"Comoros","state_name":"Grande Comore","state_code":"G"},{"name":"Koua","country_name":"Comoros","state_name":"Grande Comore","state_code":"G"},{"name":"Madjeouéni","country_name":"Comoros","state_name":"Grande Comore","state_code":"G"},{"name":"Mandza","country_name":"Comoros","state_name":"Grande Comore","state_code":"G"},{"name":"Mavingouni","country_name":"Comoros","state_name":"Grande Comore","state_code":"G"},{"name":"Mbéni","country_name":"Comoros","state_name":"Grande Comore","state_code":"G"},{"name":"Mitsamiouli","country_name":"Comoros","state_name":"Grande Comore","state_code":"G"},{"name":"Mitsoudjé","country_name":"Comoros","state_name":"Grande Comore","state_code":"G"},{"name":"Mnoungou","country_name":"Comoros","state_name":"Grande Comore","state_code":"G"},{"name":"Mohoro","country_name":"Comoros","state_name":"Grande Comore","state_code":"G"},{"name":"Moroni","country_name":"Comoros","state_name":"Grande Comore","state_code":"G"},{"name":"Mtsamdou","country_name":"Comoros","state_name":"Grande Comore","state_code":"G"},{"name":"Mvouni","country_name":"Comoros","state_name":"Grande Comore","state_code":"G"},{"name":"Nioumamilima","country_name":"Comoros","state_name":"Grande Comore","state_code":"G"},{"name":"Ntsaouéni","country_name":"Comoros","state_name":"Grande Comore","state_code":"G"},{"name":"Ntsoudjini","country_name":"Comoros","state_name":"Grande Comore","state_code":"G"},{"name":"Ouellah","country_name":"Comoros","state_name":"Grande Comore","state_code":"G"},{"name":"Ouhozi","country_name":"Comoros","state_name":"Grande Comore","state_code":"G"},{"name":"Ourovéni","country_name":"Comoros","state_name":"Grande Comore","state_code":"G"},{"name":"Oussivo","country_name":"Comoros","state_name":"Grande Comore","state_code":"G"},{"name":"Salimani","country_name":"Comoros","state_name":"Grande Comore","state_code":"G"},{"name":"Séléa","country_name":"Comoros","state_name":"Grande Comore","state_code":"G"},{"name":"Singani","country_name":"Comoros","state_name":"Grande Comore","state_code":"G"},{"name":"Tsidjé","country_name":"Comoros","state_name":"Grande Comore","state_code":"G"},{"name":"Vanadjou","country_name":"Comoros","state_name":"Grande Comore","state_code":"G"},{"name":"Vanambouani","country_name":"Comoros","state_name":"Grande Comore","state_code":"G"},{"name":"Djoyézi","country_name":"Comoros","state_name":"Mohéli","state_code":"M"},{"name":"Fomboni","country_name":"Comoros","state_name":"Mohéli","state_code":"M"},{"name":"Hoani","country_name":"Comoros","state_name":"Mohéli","state_code":"M"},{"name":"Mtakoudja","country_name":"Comoros","state_name":"Mohéli","state_code":"M"},{"name":"Nioumachoua","country_name":"Comoros","state_name":"Mohéli","state_code":"M"},{"name":"Ouanani","country_name":"Comoros","state_name":"Mohéli","state_code":"M"},{"name":"Ziroudani","country_name":"Comoros","state_name":"Mohéli","state_code":"M"}]